helper_string/__init__.py
helper_string-0.4.1.dist-info/DESCRIPTION.rst
helper_string-0.4.1.dist-info/METADATA
helper_string-0.4.1.dist-info/RECORD
helper_string-0.4.1.dist-info/WHEEL
helper_string-0.4.1.dist-info/metadata.json
helper_string-0.4.1.dist-info/top_level.txt
