Metadata-Version: 2.0
Name: helper-string
Version: 0.4.1
Summary: String Helper
Home-page: https://github.com/shuge/helper_string
Author: Shuge Lee
Author-email: shuge.lee@gmail.com
License: MIT License
Platform: UNKNOWN
